LICENSE.txt
README.md
setup.py
linereg/__init__.py
linereg/linereg.py
linereg.egg-info/PKG-INFO
linereg.egg-info/SOURCES.txt
linereg.egg-info/dependency_links.txt
linereg.egg-info/requires.txt
linereg.egg-info/top_level.txt